{
"SCV100CM2": {
"fuel": "Carb",
"start": "Self",
"brake": "Drum"
},
"SCV100CM5": {
"fuel": "Carb",
"start": "Self",
"brake": "Drum",
"cbs": "Yes"
},
"SCV1109": {
"fuel": "Carb",
"start": "Self",
"brake": "Drum",
"cbs": "Yes"
},
"SCV110B": {
"fuel": "Carb",
"start": "Self",
"brake": "Drum",
"cbs": "Yes"
},
"SCV110D": {
"fuel": "Carb",
"start": "Self",
"brake": "Drum",
"cbs": "Yes"
},
"SCV110E": {
"fuel": "Carb",
"start": "Self",
"brake": "Drum",
"cbs": "Yes"
},
"SCV110F": {
"fuel": "Carb",
"start": "Self",
"brake": "Drum",
"cbs": "Yes"
},
"SCV110G": {
"fuel": "Carb",
"start": "Self",
"brake": "Drum",
"cbs": "Yes"
},
"SCV110H": {
"fuel": "Carb",
"start": "Self",
"brake": "Drum",
"cbs": "Yes"
},
"SCV110J": {
"fuel": "Carb",
"start": "Self",
"brake": "Drum",
"cbs": "Yes"
},
"SCV110L": {
"fuel": "Carb",
"start": "Self",
"brake": "Drum",
"cbs": "Yes"
},
"SCV110LI": {
"fuel": "FI",
"start": "Silent",
"brake": "Drum",
"cbs": "Yes"
},
"SCV110M": {
"fuel": "FI",
"start": "Silent",
"brake": "Drum",
"cbs": "Yes"
},
"SCV110N": {
"fuel": "FI",
"start": "Silent",
"brake": "Drum",
"cbs": "Yes"
},
"SCV110P/SR": {
"fuel": "FI",
"start": "Silent",
"brake": "Drum",
"cbs": "Yes"
},
"SCV110S": {
"fuel": "FI",
"start": "Silent",
"brake": "Drum",
"cbs": "Yes"
},
"SCV110T": {
"fuel": "FI",
"start": "Silent",
"brake": "Drum",
"cbs": "Yes"
},
"SCV110HE": {
"fuel": "Carb",
"start": "Self",
"brake": "Drum",
"cbs": "Yes"
},
"SCV110HF": {
"fuel": "Carb",
"start": "Self",
"brake": "Drum",
"cbs": "Yes"
},
"SCV110HH": {
"fuel": "Carb",
"start": "Self",
"brake": "Drum",
"cbs": "Yes"
},
"SCV110HK": {
"fuel": "Carb",
"start": "Self",
"brake": "Drum",
"cbs": "Yes"
},
"SCV125E": {
"fuel": "Carb",
"start": "Self",
"brake": "Disc",
"cbs": "Yes"
},
"SCV125FP": {
"fuel": "FI",
"start": "Silent",
"brake": "Disc",
"cbs": "Yes"
},
"SCV125G": {
"fuel": "Carb",
"start": "Self",
"brake": "Disc",
"cbs": "Yes"
},
"SCV125H": {
"fuel": "Carb",
"start": "Self",
"brake": "Disc",
"cbs": "Yes"
},
"SCV125K": {
"fuel": "Carb",
"start": "Self",
"brake": "Disc",
"cbs": "Yes"
},
"SCV125L": {
"fuel": "FI",
"start": "Silent",
"brake": "Disc",
"cbs": "Yes"
},
"SCV125N": {
"fuel": "FI",
"start": "Silent",
"brake": "Disc",
"cbs": "Yes"
},
"SCV125S": {
"fuel": "FI",
"start": "Silent",
"brake": "Disc",
"cbs": "Yes"
},
"SCV125T": {
"fuel": "FI",
"start": "Silent",
"brake": "Disc",
"cbs": "Yes"
},
"SCV100G8": {
"fuel": "Carb",
"start": "Self",
"brake": "Disc",
"cbs": "Yes"
},
"SCV110GA": {
"fuel": "Carb",
"start": "Self",
"brake": "Disc",
"cbs": "Yes"
},
"SCV110GC": {
"fuel": "Carb",
"start": "Self",
"brake": "Disc",
"cbs": "Yes"
},
"SCV110GD": {
"fuel": "Carb",
"start": "Self",
"brake": "Drum",
"cbs": "Yes"
},
"SCV110GF": {
"fuel": "Carb",
"start": "Self",
"brake": "Drum",
"cbs": "Yes"
},
"SCV110GFD": {
"fuel": "Carb",
"start": "Self",
"brake": "Disc",
"cbs": "Yes"
},
"SCV110GFF": {
"fuel": "Carb",
"start": "Self",
"brake": "Disc",
"cbs": "Yes"
},
"SCV110GFH": {
"fuel": "Carb",
"start": "Silent",
"brake": "Disc",
"cbs": "Yes"
},
"SCV110GFK": {
"fuel": "Carb",
"start": "Silent",
"brake": "Disc",
"cbs": "Yes"
},
"SCV110GH": {
"fuel": "Carb",
"start": "Silent",
"brake": "Drum",
"cbs": "Yes"
},
"SCV110GK": {
"fuel": "Carb",
"start": "Silent",
"brake": "Drum",
"cbs": "Yes"
},
"NVB110H": {
"fuel": "Carb",
"start": "Self",
"brake": "Drum"
},
"SCV100F3": {
"fuel": "Carb",
"start": "Self",
"brake": "Drum",
"cbs": "Yes"
},
"SCV100F5": {
"fuel": "Carb",
"start": "Self",
"brake": "Drum",
"cbs": "Yes"
},
"SCV100F9": {
"fuel": "Carb",
"start": "Self",
"brake": "Drum",
"cbs": "Yes"
},
"SCV100FA": {
"fuel": "Carb",
"start": "Self",
"brake": "Drum",
"cbs": "Yes"
},
"SCV110FBC": {
"fuel": "Carb",
"start": "Self",
"brake": "Drum",
"cbs": "Yes"
},
"SCV110FBH": {
"fuel": "Carb",
"start": "Self",
"brake": "Drum",
"cbs": "Yes"
},
"SCV110FBK": {
"fuel": "Carb",
"start": "Self",
"brake": "Drum",
"cbs": "Yes"
},
"SCV110FBL": {
"fuel": "FI",
"start": "Silent",
"brake": "Drum",
"cbs": "Yes"
},
"SCV110FBR": {
"fuel": "FI",
"start": "Silent",
"brake": "Drum",
"cbs": "Yes"
},
"SCV110FBS": {
"fuel": "FI",
"start": "Silent",
"brake": "Drum",
"cbs": "Yes"
},
"SCV110FC": {
"fuel": "Carb",
"start": "Self",
"brake": "Drum",
"cbs": "Yes"
},
"SCV110FD": {
"fuel": "Carb",
"start": "Self",
"brake": "Drum",
"cbs": "Yes"
},
"SCV110FF": {
"fuel": "Carb",
"start": "Self",
"brake": "Drum",
"cbs": "Yes"
},
"SCV110FH": {
"fuel": "Carb",
"start": "Self",
"brake": "Drum",
"cbs": "Yes"
},
"SCV110FK": {
"fuel": "Carb",
"start": "Self",
"brake": "Drum",
"cbs": "Yes"
},
"SCV110FL": {
"fuel": "FI",
"start": "Silent",
"brake": "Drum",
"cbs": "Yes"
},
"SCV110FM": {
"fuel": "FI",
"start": "Silent",
"brake": "Drum",
"cbs": "Yes"
},
"SCV110FP": {
"fuel": "FI",
"start": "Silent",
"brake": "Drum",
"cbs": "Yes"
},
"SCV110FR": {
"fuel": "FI",
"start": "Silent",
"brake": "Drum",
"cbs": "Yes"
},
"SCV110FS": {
"fuel": "FI",
"start": "Silent",
"brake": "Drum",
"cbs": "Yes"
},
"SCV125SBR": {
"fuel": "FI",
"start": "Silent",
"brake": "Disc",
"cbs": "Yes"
},
"SCV125SBT": {
"fuel": "FI",
"start": "Silent",
"brake": "Disc",
"cbs": "Yes"
},
"SCV125SR": {
"fuel": "FI",
"start": "Silent",
"brake": "Disc",
"cbs": "Yes"
},
"SCV125ST": {
"fuel": "FI",
"start": "Silent",
"brake": "Disc",
"cbs": "Yes"
},
"SC1504": {
"fuel": "Carb",
"start": "Kick",
"brake": "Drum"
},
"SC1505": {
"fuel": "Carb",
"start": "Kick",
"brake": "Drum"
},
"SCV125SJ": {
"fuel": "Carb",
"start": "Self",
"brake": "Disc",
"cbs": "Yes"
},
"SCV125SK": {
"fuel": "Carb",
"start": "Self",
"brake": "Disc",
"cbs": "Yes"
},
"SCV125SL": {
"fuel": "FI",
"start": "Silent",
"brake": "Disc",
"cbs": "Yes"
},
"SCV125SM": {
"fuel": "FI",
"start": "Silent",
"brake": "Disc",
"cbs": "Yes"
},
"SCV125SN": {
"fuel": "FI",
"start": "Silent",
"brake": "Disc",
"cbs": "Yes"
},
"NVA110BK": {
"fuel": "Carb",
"start": "Self",
"brake": "Drum"
},
"NVA110G": {
"fuel": "Carb",
"start": "Self",
"brake": "Drum"
},
"NVA110H": {
"fuel": "Carb",
"start": "Self",
"brake": "Drum"
},
"NVA110K": {
"fuel": "Carb",
"start": "Self",
"brake": "Drum"
},
"CB500XAM": {
"fuel": "FI",
"brake": "Disc"
},
"CRF1000DH": {
"fuel": "FI",
"brake": "Disc",
"wheel": "Spoke"
},
"CRF1000DJ": {
"fuel": "FI",
"brake": "Disc",
"wheel": "Spoke"
},
"CRF1000DK": {
"fuel": "FI",
"brake": "Disc",
"wheel": "Spoke"
},
"CRF1100AL2L": {
"fuel": "FI",
"brake": "Disc",
"wheel": "Spoke"
},
"CRF1100AL2M": {
"fuel": "FI",
"brake": "Disc",
"wheel": "Spoke"
},
"CRF1100AL2N": {
"fuel": "FI",
"brake": "Disc",
"wheel": "Spoke"
},
"CRF1100DL2L": {
"fuel": "FI",
"brake": "Disc",
"wheel": "Spoke"
},
"CRF1100DL2M": {
"fuel": "FI",
"brake": "Disc",
"wheel": "Spoke"
},
"CRF1100DL2N": {
"fuel": "FI",
"brake": "Disc",
"wheel": "Spoke"
},
"CBF160MAJ": {
"fuel": "Carb",
"start": "Self",
"brake": "Disc"
},
"CBF160MAK": {
"fuel": "Carb",
"start": "Self",
"brake": "Disc"
},
"CBF160MG": {
"fuel": "Carb",
"start": "Self",
"brake": "Disc"
},
"CBF160MH": {
"fuel": "Carb",
"start": "Self",
"brake": "Disc"
},
"CBF160MJ": {
"fuel": "Carb",
"start": "Self",
"brake": "Disc"
},
"CBF125MG": {
"fuel": "Carb",
"start": "Self",
"brake": "Disc"
},
"CBF125MH": {
"fuel": "Carb",
"start": "Self",
"brake": "Disc"
},
"CBF125MJ/MK": {
"fuel": "Carb",
"start": "Self",
"brake": "Disc"
},
"CBF1256": {
"fuel": "Carb",
"start": "Kick",
"brake": "Disc",
"wheel": "Spoke"
},
"CBF125A": {
"fuel": "Carb",
"start": "Self",
"brake": "Disc",
"wheel": "Spoke"
},
"CBF125BH": {
"fuel": "Carb",
"start": "Self",
"brake": "Disc"
},
"CBF125C": {
"fuel": "Carb",
"start": "Kick",
"brake": "Drum",
"wheel": "Spoke"
},
"CBF125C9": {
"fuel": "FI",
"start": "Self",
"brake": "Disc"
},
"CBF125CA": {
"fuel": "Carb",
"start": "Self",
"brake": "Disc",
"wheel": "Spoke"
},
"CBF125CC": {
"fuel": "Carb",
"start": "Kick",
"brake": "Disc"
},
"CBF125CL": {
"fuel": "FI",
"start": "Silent",
"brake": "Disc"
},
"CBF125F": {
"fuel": "Carb",
"start": "Self",
"brake": "Disc"
},
"CBF125H": {
"fuel": "Carb",
"start": "Self",
"brake": "Disc"
},
"CBF125J/K": {
"fuel": "Carb",
"start": "Self",
"brake": "Disc"
},
"CBF125L": {
"fuel": "FI",
"start": "Silent",
"brake": "Disc"
},
"CBF125L3": {
"fuel": "FI",
"start": "Silent",
"brake": "Disc"
},
"CBF125M7": {
"fuel": "Carb",
"start": "Self",
"brake": "Disc",
"wheel": "Spoke"
},
"CBF125MC9": {
"fuel": "Carb",
"start": "Self",
"brake": "Disc"
},
"CBF125MCA": {
"fuel": "Carb",
"start": "Self",
"brake": "Disc",
"wheel": "Spoke"
},
"CBF125MCC": {
"fuel": "Carb",
"start": "Self",
"brake": "Disc"
},
"CBF125N": {
"fuel": "FI",
"start": "Silent",
"brake": "Disc"
},
"CBF125P": {
"fuel": "FI",
"start": "Silent",
"brake": "Disc"
},
"CBF125S": {
"fuel": "FI",
"start": "Silent",
"brake": "Disc"
},
"CBF125T": {
"fuel": "FI",
"start": "Silent",
"brake": "Disc"
},
"CBF150MD": {
"fuel": "Carb",
"start": "Kick",
"brake": "Disc"
},
"CBF110A": {
"fuel": "Carb",
"start": "Kick",
"brake": "Drum"
},
"CBF110C": {
"fuel": "Carb",
"start": "Kick",
"brake": "Drum"
},
"CBF110E": {
"fuel": "Carb",
"start": "Kick",
"brake": "Drum"
},
"CBF110MA": {
"fuel": "Carb",
"start": "Self",
"brake": "Disc"
},
"CBF110MC": {
"fuel": "Carb",
"start": "Self",
"brake": "Disc"
},
"CBF110ME": {
"fuel": "Carb",
"start": "Self",
"brake": "Disc"
},
"CBF110MSE": {
"fuel": "Carb",
"start": "Self",
"brake": "Disc"
},
"CBF1505": {
"fuel": "Carb",
"start": "Self",
"brake": "Disc",
"wheel": "Spoke"
},
"CBF1506": {
"fuel": "Carb",
"start": "Self",
"brake": "Disc",
"wheel": "Spoke"
},
"CBF1507": {
"fuel": "Carb",
"start": "Self",
"brake": "Disc",
"wheel": "Spoke"
},
"CBF150M5": {
"fuel": "Carb",
"start": "Self",
"brake": "Disc",
"wheel": "Spoke"
},
"CBF150M6": {
"fuel": "Carb",
"start": "Self",
"brake": "Disc",
"wheel": "Spoke"
},
"CBF150M7": {
"fuel": "Carb",
"start": "Self",
"brake": "Disc",
"wheel": "Spoke"
},
"CBF150M9": {
"fuel": "Carb",
"start": "Self",
"brake": "Disc"
},
"CBF150MA": {
"fuel": "Carb",
"start": "Self",
"brake": "Disc"
},
"CBF150MH": {
"fuel": "Carb",
"start": "Self",
"brake": "Disc"
},
"CBF150MK": {
"fuel": "Carb",
"start": "Self",
"brake": "Disc"
},
"CBF160AL": {
"fuel": "FI",
"start": "Kick",
"brake": "Disc"
},
"CBF160AR": {
"fuel": "FI",
"start": "Kick",
"brake": "Disc"
},
"CBF160AS": {
"fuel": "FI",
"start": "Kick",
"brake": "Disc"
},
"CBF160F": {
"fuel": "Carb",
"start": "Kick",
"brake": "Disc"
},
"CBF160G": {
"fuel": "Carb",
"start": "Kick",
"brake": "Disc"
},
"CBF160H": {
"fuel": "Carb",
"start": "Kick",
"brake": "Disc"
},
"CBF150MB": {
"fuel": "Carb",
"start": "Self",
"brake": "Disc"
},
"CBF150MC": {
"fuel": "Carb",
"start": "Self",
"brake": "Disc"
},
"CBF125ZT": {
"fuel": "FI",
"start": "Silent",
"brake": "Disc"
},
"CB190XN": {
"fuel": "FI",
"brake": "Disc"
},
"CB190XR": {
"fuel": "FI",
"brake": "Disc"
},
"CB190XS": {
"fuel": "FI",
"brake": "Disc"
},
"MC300AN": {
"fuel": "FI",
"brake": "Disc"
},
"MC300AP": {
"fuel": "FI",
"brake": "Disc"
},
"MC300AS": {
"fuel": "FI",
"brake": "Disc"
},
"CBF300NAK": {
"fuel": "FI",
"brake": "Disc"
},
"CBF300NAN": {
"fuel": "FI",
"brake": "Disc"
},
"CBF300NAR": {
"fuel": "FI",
"brake": "Disc"
},
"CB350CR": {
"fuel": "FI",
"brake": "Disc"
},
"CB350CS": {
"fuel": "FI",
"brake": "Disc"
},
"CB350CSR": {
"fuel": "FI",
"brake": "Disc"
},
"CB350CSS": {
"fuel": "FI",
"brake": "Disc"
},
"CB350CST": {
"fuel": "FI",
"brake": "Disc"
},
"CB350CT": {
"fuel": "FI",
"brake": "Disc"
},
"CB650RAM": {
"fuel": "FI",
"start": "Self",
"brake": "Disc"
},
"CB650RAN": {
"fuel": "FI",
"start": "Self",
"brake": "Disc"
},
"CBF1259": {
"fuel": "FI",
"start": "Self",
"brake": "Disc"
},
"CBF125M9/MF": {
"fuel": "FI",
"start": "Self",
"brake": "Disc"
},
"CBF125MA": {
"fuel": "Carb",
"start": "Self",
"brake": "Disc"
},
"CBF125MB": {
"fuel": "FI",
"start": "Self",
"brake": "Disc"
},
"CBF125MC": {
"fuel": "Carb",
"start": "Self",
"brake": "Disc"
},
"CBR150RC": {
"fuel": "FI",
"brake": "Disc"
},
"CBR150RG": {
"fuel": "FI",
"brake": "Disc"
},
"CBR250RAB": {
"fuel": "FI",
"start": "Self",
"brake": "Disc"
},
"CBR250RAC": {
"fuel": "FI",
"start": "Self",
"brake": "Disc"
},
"CBR250RAD": {
"fuel": "FI",
"start": "Self",
"brake": "Disc"
},
"CBR250RAG": {
"fuel": "FI",
"start": "Self",
"brake": "Disc"
},
"CBR250RAH": {
"fuel": "FI",
"start": "Self",
"brake": "Disc"
},
"CBR250RAJ": {
"fuel": "FI",
"start": "Self",
"brake": "Disc"
},
"CBR250RB": {
"fuel": "FI",
"start": "Self",
"brake": "Disc"
},
"CBR250RC": {
"fuel": "FI",
"start": "Self",
"brake": "Disc"
},
"CBR250RD": {
"fuel": "FI",
"start": "Self",
"brake": "Disc"
},
"CBR250RG": {
"fuel": "FI",
"start": "Self",
"brake": "Disc"
},
"CBR250RH": {
"fuel": "FI",
"start": "Self",
"brake": "Disc"
},
"CBR250RJ": {
"fuel": "FI",
"start": "Self",
"brake": "Disc"
},
"CBR650FAG": {
"fuel": "FI",
"start": "Self",
"brake": "Disc"
},
"CBR650FAJ": {
"fuel": "FI",
"start": "Self",
"brake": "Disc"
},
"CBR650RAL": {
"fuel": "FI",
"start": "Self",
"brake": "Disc"
},
"CBR650RAM": {
"fuel": "FI",
"start": "Self",
"brake": "Disc"
},
"CBR650RAN": {
"fuel": "FI",
"start": "Self",
"brake": "Disc"
},
"CB110C2F": {
"fuel": "Carb",
"start": "Kick",
"brake": "Drum"
},
"CB110C2G": {
"fuel": "Carb",
"start": "Kick",
"brake": "Drum"
},
"CB110C2H": {
"fuel": "Carb",
"start": "Kick",
"brake": "Drum"
},
"CB110C2K": {
"fuel": "Carb",
"start": "Kick",
"brake": "Drum"
},
"CB110C2MG": {
"fuel": "Carb",
"start": "Kick",
"brake": "Drum"
},
"CB110C2MH": {
"fuel": "Carb",
"start": "Kick",
"brake": "Drum"
},
"CB110C2MK": {
"fuel": "Carb",
"start": "Kick",
"brake": "Drum"
},
"CB110C3MM": {
"fuel": "FI",
"start": "Kick",
"brake": "Drum"
},
"CB110CMDK": {
"fuel": "Carb",
"start": "Kick",
"brake": "Drum"
},
"CB110CMDM": {
"fuel": "FI",
"start": "Kick",
"brake": "Drum"
},
"CB110CMDN": {
"fuel": "FI",
"start": "Kick",
"brake": "Drum"
},
"CB110CMDR": {
"fuel": "FI",
"start": "Kick",
"brake": "Drum"
},
"CB110CE": {
"fuel": "Carb",
"start": "Kick",
"brake": "Drum",
"wheel": "Spoke"
},
"CB110CF": {
"fuel": "Carb",
"start": "Kick",
"brake": "Drum",
"wheel": "Spoke"
},
"CB110CG": {
"fuel": "Carb",
"start": "Kick",
"brake": "Drum",
"wheel": "Spoke"
},
"CB110CME": {
"fuel": "Carb",
"start": "Kick",
"brake": "Drum"
},
"CB110CMF": {
"fuel": "Carb",
"start": "Kick",
"brake": "Drum"
},
"CB110CMG": {
"fuel": "Carb",
"start": "Kick",
"brake": "Drum"
},
"CB110CMH": {
"fuel": "Carb",
"start": "Kick",
"brake": "Drum"
},
"CB110AMF": {
"fuel": "Carb",
"start": "Kick",
"brake": "Drum"
},
"CB110AMH": {
"fuel": "Carb",
"start": "Kick",
"brake": "Drum"
},
"CB110BK": {
"fuel": "Carb",
"start": "Kick",
"brake": "Drum"
},
"CB110D": {
"fuel": "Carb",
"start": "Kick",
"brake": "Drum",
"wheel": "Spoke"
},
"CB110E": {
"fuel": "Carb",
"start": "Kick",
"brake": "Drum",
"wheel": "Spoke"
},
"CB110J": {
"fuel": "Carb",
"start": "Kick",
"brake": "Drum",
"wheel": "Spoke"
},
"CB110MD": {
"fuel": "Carb",
"start": "Kick",
"brake": "Drum"
},
"CB110ME": {
"fuel": "Carb",
"start": "Kick",
"brake": "Drum"
},
"CB350DM": {
"fuel": "FI",
"brake": "Disc"
},
"CB350DP": {
"fuel": "FI",
"brake": "Disc"
},
"CB350DS": {
"fuel": "FI",
"brake": "Disc"
},
"CB350DSM": {
"fuel": "FI",
"brake": "Disc"
},
"CB350DSN": {
"fuel": "FI",
"brake": "Disc"
},
"CB350DSP/DSR": {
"fuel": "FI",
"brake": "Disc"
},
"CB350DSS": {
"fuel": "FI",
"brake": "Disc"
},
"CB350RSM": {
"fuel": "FI",
"brake": "Disc"
},
"CB350RSP/RSR": {
"fuel": "FI",
"brake": "Disc"
},
"CB350RSS": {
"fuel": "FI",
"brake": "Disc"
},
"CBF190MAL": {
"fuel": "FI",
"brake": "Disc"
},
"CBF190MAM": {
"fuel": "FI",
"brake": "Disc"
},
"CBF190MAN": {
"fuel": "FI",
"brake": "Disc"
},
"CBF190MAR": {
"fuel": "FI",
"brake": "Disc"
},
"CBF190MAS": {
"fuel": "FI",
"brake": "Disc"
},
"CBF110BEN": {
"fuel": "FI",
"start": "Silent",
"brake": "Drum"
},
"CBF110BER": {
"fuel": "FI",
"start": "Silent",
"brake": "Drum"
},
"CBF110BES": {
"fuel": "FI",
"start": "Silent",
"brake": "Drum"
},
"CBF110BK": {
"fuel": "Carb",
"start": "Kick",
"brake": "Drum"
},
"CBF110BL": {
"fuel": "FI",
"start": "Silent",
"brake": "Drum"
},
"CBF110BN": {
"fuel": "FI",
"start": "Silent",
"brake": "Drum"
},
"CBF110G": {
"fuel": "Carb",
"start": "Kick",
"brake": "Drum"
},
"CBF110H": {
"fuel": "Carb",
"start": "Kick",
"brake": "Drum"
},
"CBF110J": {
"fuel": "Carb",
"start": "Kick",
"brake": "Drum"
},
"CBF110SBEN": {
"fuel": "FI",
"start": "Silent",
"brake": "Disc"
},
"CBF110SBER": {
"fuel": "FI",
"start": "Silent",
"brake": "Disc"
},
"CBF110SBES": {
"fuel": "FI",
"start": "Silent",
"brake": "Disc"
},
"CBF110SBK": {
"fuel": "Carb",
"start": "Kick",
"brake": "Disc"
},
"CBF110SBL": {
"fuel": "FI",
"start": "Silent",
"brake": "Disc"
},
"CBF110SBN": {
"fuel": "FI",
"start": "Silent",
"brake": "Disc"
},
"CBF110SG": {
"fuel": "Carb",
"start": "Kick",
"brake": "Disc"
},
"CBF110SH": {
"fuel": "Carb",
"start": "Kick",
"brake": "Disc"
},
"CBF110SJ": {
"fuel": "Carb",
"start": "Kick",
"brake": "Disc"
},
"CD100RNP": {
"fuel": "FI",
"start": "Kick",
"brake": "Drum"
},
"CD100RNS": {
"fuel": "FI",
"start": "Kick",
"brake": "Drum"
},
"CD100RNT": {
"fuel": "FI",
"start": "Kick",
"brake": "Drum"
},
"CBF125MEFS": {
"fuel": "FI",
"start": "Silent",
"brake": "Disc"
},
"CBF125MEFT": {
"fuel": "FI",
"start": "Silent",
"brake": "Disc"
},
"CBF125MEN": {
"fuel": "FI",
"start": "Silent",
"brake": "Disc"
},
"CBF125MEP": {
"fuel": "FI",
"start": "Silent",
"brake": "Disc"
},
"CBF125MER": {
"fuel": "FI",
"start": "Silent",
"brake": "Disc"
},
"CBF125MFS": {
"fuel": "FI",
"start": "Silent",
"brake": "Drum"
},
"CBF125ML": {
"fuel": "FI",
"start": "Silent",
"brake": "Disc"
},
"CBF125MN": {
"fuel": "FI",
"start": "Silent",
"brake": "Disc"
},
"CBF125MP": {
"fuel": "FI",
"start": "Silent",
"brake": "Drum"
},
"CBF160FSR": {
"fuel": "FI",
"start": "Kick",
"brake": "Disc"
},
"CBF160FSS": {
"fuel": "FI",
"brake": "Disc"
},
"CBF160FSJ": {
"fuel": "Carb",
"start": "Kick",
"brake": "Disc"
},
"CBF160FSK": {
"fuel": "Carb",
"start": "Kick",
"brake": "Disc"
},
"CBF160FSM": {
"fuel": "FI",
"start": "Kick",
"brake": "Disc"
},
"CBF160FSN": {
"fuel": "FI",
"start": "Kick",
"brake": "Disc"
}
}